setup.py
avrolight/__init__.py
avrolight/container.py
avrolight/io.py
avrolight/json.py
avrolight/registry.py
avrolight/schema.py
avrolight.egg-info/PKG-INFO
avrolight.egg-info/SOURCES.txt
avrolight.egg-info/dependency_links.txt
avrolight.egg-info/requires.txt
avrolight.egg-info/top_level.txt