Metadata-Version: 1.1
Name: avrolight
Version: 1.0.7
Summary: A light and fast implementation of the avro message format
Home-page: https://github.com/oliverbestmann/avrolight
Author: Oliver Bestmann
Author-email: oliver.bestmann@googlemail.com
License: MIT
Platform: UNKNOWN
Classifier: Development Status :: 4 - Beta
Classifier: License :: OSI Approved :: MIT License
Classifier: Programming Language :: Python :: 3.4
